firstry/__init__.py
firstry/_main.py
firstry-0.0.3.dist-info/DESCRIPTION.rst
firstry-0.0.3.dist-info/METADATA
firstry-0.0.3.dist-info/RECORD
firstry-0.0.3.dist-info/WHEEL
firstry-0.0.3.dist-info/entry_points.txt
firstry-0.0.3.dist-info/metadata.json
firstry-0.0.3.dist-info/top_level.txt
