Metadata-Version: 2.0
Name: firstry
Version: 0.0.3
Summary: A Python package to print
Home-page: UNKNOWN
Author: ANOOP SINGH RANA
Author-email: apours986@gmail.com
License: MIT
Platform: UNKNOWN
Classifier: Programming Language :: Python :: 3
